iota/__init__.py
iota/analysis/__init__.py
iota/analysis/iota_analysis.py
iota/base/__init__.py
iota/base/importer.py
iota/base/info.py
iota/base/processor.py
iota/command_line/__init__.py
iota/command_line/iota_filter_pickles.py
iota/command_line/iota_gui_launch.py
iota/command_line/iota_run.py
iota/command_line/iota_single_image.py
iota/command_line/iota_track_images.py
iota/etc/__init__.py
iota/etc/iota_cctbx_ha14.py
iota/etc/iota_tracker.py
iota/etc/iota_vis_integration.py
iota/gui/__init__.py
iota/gui/base.py
iota/gui/controls.py
iota/gui/dialogs.py
iota/gui/iota_ui_frames.py
iota/gui/phil_controls.py
iota/gui/plotter.py
iota/init/__init__.py
iota/init/image_import.py
iota/init/iota_init.py
iota/init/iota_input.py
iota/processing/__init__.py
iota/processing/processing.py
iota/threads/__init__.py
iota/threads/analysis_threads.py
iota/threads/iota_threads.py
iota/threads/other_threads.py
iota/utils/__init__.py
iota/utils/input_finder.py
iota/utils/utils.py
iota-1.5.4.dist-info/LICENSE.txt
iota-1.5.4.dist-info/METADATA
iota-1.5.4.dist-info/WHEEL
iota-1.5.4.dist-info/entry_points.txt
iota-1.5.4.dist-info/top_level.txt
iota-1.5.4.dist-info/RECORD
