Metadata-Version: 2.1
Name: iota
Version: 1.5.4
Summary: IOTA: Integration Optimization, Triage and Analysis
Home-page: https://github.com/ssrl-px/iota
Download-URL: https://github.com/ssrl-px/iota/releases
Author: Leland Stanford Junior University
Author-email: scientificsoftware@diamond.ac.uk
License: BSD
Classifier: Development Status :: 5 - Production/Stable
Classifier: License :: OSI Approved :: BSD License
Classifier: Programming Language :: Python :: 2
Classifier: Programming Language :: Python :: 2.7
Classifier: Programming Language :: Python :: 3
Classifier: Programming Language :: Python :: 3.5
Classifier: Programming Language :: Python :: 3.6
Classifier: Programming Language :: Python :: 3.7
Classifier: Programming Language :: Python :: 3.8
Classifier: Operating System :: POSIX :: Linux
License-File: LICENSE.txt
Requires-Dist: matplotlib
Requires-Dist: numpy
Requires-Dist: six
Requires-Dist: wxpython
